aiq/__init__.py
aiq/aiq.py
aiq/classify.py
aiq/common.py
aiq/embed.py
aiq/label.py
aiq/train.py
aiq_cli-0.1.2.dist-info/LICENSE
aiq_cli-0.1.2.dist-info/METADATA
aiq_cli-0.1.2.dist-info/WHEEL
aiq_cli-0.1.2.dist-info/entry_points.txt
aiq_cli-0.1.2.dist-info/top_level.txt
aiq_cli-0.1.2.dist-info/RECORD
