Metadata-Version: 2.1
Name: aiq-cli
Version: 0.1.2
Summary: Train classification models from the command line.
Author: Benjamin Anderson
License: MIT
License-File: LICENSE
Requires-Dist: scikit-learn>=1.3.1
Requires-Dist: fire
Requires-Dist: pandas
Requires-Dist: onnxruntime
Requires-Dist: transformers>=4.44
Requires-Dist: joblib
Requires-Dist: numpy<2
Requires-Dist: rich>=13.7.0
Requires-Dist: onnx-embedding-models>=0.0.16
Requires-Dist: openai==1.46.1
Requires-Dist: python-dotenv
